langgraph_reflection/__init__.py
langgraph_reflection-0.0.1.dist-info/METADATA
langgraph_reflection-0.0.1.dist-info/WHEEL
langgraph_reflection-0.0.1.dist-info/top_level.txt
langgraph_reflection-0.0.1.dist-info/RECORD
