Metadata-Version: 2.2
Name: langgraph-reflection
Version: 0.0.1
Summary: LangGraph agent that runs a reflection step
Author: Harrison Chase
Requires-Python: >=3.11
Requires-Dist: langgraph
Requires-Dist: mypy>=1.8.0
Requires-Dist: langchain>=0.1.0
